{
    "timestamp": "12-25-2023 20:32:57",
    "verseRef": "Luke 5:15",
    "bestBHT": {
        "bht": "Despite Jesus commanding the man to stay silent about his healing, the news of the miraculous cure spread rapidly and the crowds kept coming together to be healed of their infirmities. The more Jesus charged the man to keep silent, the more the news blazed abroad, fueling the excitement and gratitude of those who experienced the healing. The fame of Jesus grew and circulated throughout the region, drawing in great multitudes who came together to hear his teachings and seek healing from him.",
        "wordCount": 83,
        "quoteTokenProportion": 32.69,
        "qualityScore": 1.4970038484039465,
        "qualityScoreNormalizedComparedToV2BHTs": 41.12,
        "commentatorTierSimilarities": [
            25.79,
            0.0,
            74.21
        ],
        "generationAttempt": 3
    },
    "choicestQuotes": {
        "Henry Alford": [
            "15.] The reason of this is stated in Mark, ver. 45, to be the disobedience of the leper to the Lord\u2019s command."
        ],
        "Jamieson-Fausset-Brown": [
            "15. But so, &amp;c.\u2014(See :-). ",
            "\t",
            " :-. PARALYTIC",
            "\tHEALED. ",
            "\t",
            "(See on :-)."
        ],
        "Marvin Vincent": [
            "Went abroad [\u03b4\u03b9\u03b7\u03c1\u03c7\u03b5\u03c4\u03bf] . Dia, throughout the region. Wyc., the word walked about.",
            "Came together [\u03c3\u03c5\u03bd\u03b7\u03c1\u03c7\u03bf\u03bd\u03c4\u03bf] Imperfect. Kept coming together, or were coming.",
            "To be healed [\u03b8\u03b5\u03c1\u03b1\u03c0\u03b5\u03c5\u03b5\u03c3\u03b8\u03b1\u03b9] . Originally, to be an attendant, to do service; and therefore of a physician, to attend upon, or treat medically."
        ],
        "Archibald T. Robertson": [
            "So much the more (\u03bc\u03b1\u03bb\u03bb\u03bf\u03bd). Mark 1:45 has only 'much' (\u03c0\u03bf\u03bb\u03bb\u03b1, many), but Mark tells more about the effect of this disobedience.",
            "Went abroad (\u03b4\u03b9\u03b7\u03c1\u03c7\u03b5\u03c4\u03bf). Imperfect tense. The fame of Jesus kept going.",
            "Came together (\u03c3\u03c5\u03bd\u03b7\u03c1\u03c7\u03bf\u03bd\u03c4\u03bf). Imperfect tense again. The more the report spread, the more the crowds came."
        ],
        "John Gill": [
            "For the more he charged the man to keep silence, the more he blazed it abroad, being elated with the cure he received, and filled with gratitude to his benefactor.\" (Luke 5:15)",
            "And great multitudes came together to hear: him, or from him, as the Syriac, Arabic, Persic, and Ethiopic versions add; to hear the doctrines of the Gospel preached by him.\" (Luke 5:15)",
            "To be healed by him of their infirmities; their bodily weaknesses and disorders.\" (Luke 5:15)"
        ]
    },
    "choicestPrompt": "choicest prompt v0.4",
    "bhtPrompt": "bht prompt v0.8",
    "commentators": [
        "Henry Alford",
        "Jamieson-Fausset-Brown",
        "Albert Barnes",
        "Marvin Vincent",
        "John Calvin",
        "Philip Schaff",
        "Archibald T. Robertson",
        "John Gill",
        "John Wesley"
    ],
    "bhtAttemptsLimit": 5,
    "bhtAttemptsCount": 5,
    "bhtAttempts": [
        {
            "bht": "Despite Jesus commanding the man to stay quiet about his healing, the news spread rapidly and the crowds kept coming. The more Jesus tried to suppress the news, the more it blazed abroad. This led to great multitudes coming together to hear Jesus preach and seek healing from Him for their bodily weaknesses and disorders. The fame of Jesus and His ability to heal continued to go throughout the region, drawing people from all around.",
            "wordCount": 75,
            "quoteTokenProportion": 35.29,
            "qualityScore": 1.4052740123724647,
            "qualityScoreNormalizedComparedToV2BHTs": 38.07,
            "commentatorTierSimilarities": [
                31.23,
                0.0,
                68.77
            ],
            "generationAttempt": 1
        },
        {
            "bht": "Despite his command to keep silent, the news of the man's healing continued to spread far and wide. As a result, more and more people came together to hear Jesus preach and seek healing for their bodily infirmities. The fame of Jesus grew and circulated throughout the region, causing crowds from every direction to gather in anticipation of witnessing his miracles and receiving his healing touch.",
            "wordCount": 67,
            "quoteTokenProportion": 32.65,
            "qualityScore": 1.4494575349360699,
            "qualityScoreNormalizedComparedToV2BHTs": 39.54,
            "commentatorTierSimilarities": [
                29.85,
                0.0,
                70.15
            ],
            "generationAttempt": 2
        },
        {
            "bht": "Despite Jesus commanding the man to stay silent about his healing, the news of the miraculous cure spread rapidly and the crowds kept coming together to be healed of their infirmities. The more Jesus charged the man to keep silent, the more the news blazed abroad, fueling the excitement and gratitude of those who experienced the healing. The fame of Jesus grew and circulated throughout the region, drawing in great multitudes who came together to hear his teachings and seek healing from him.",
            "wordCount": 83,
            "quoteTokenProportion": 32.69,
            "qualityScore": 1.4970038484039465,
            "qualityScoreNormalizedComparedToV2BHTs": 41.12,
            "commentatorTierSimilarities": [
                25.79,
                0.0,
                74.21
            ],
            "generationAttempt": 3
        },
        {
            "bht": "Despite Jesus commanding the man to stay silent, the news of his healing spread rapidly, causing crowds to gather for healing. The more Jesus charged the man to keep silent, the more the news blazed abroad, fueling excitement. The fame of Jesus grew, drawing in multitudes who sought healing.",
            "wordCount": 49,
            "quoteTokenProportion": 28.12,
            "qualityScore": 1.371492391016066,
            "qualityScoreNormalizedComparedToV2BHTs": 36.95,
            "commentatorTierSimilarities": [
                35.12,
                0.0,
                64.88
            ],
            "generationAttempt": 4
        },
        {
            "bht": "Despite Jesus commanding the man to keep silent, news of his healing spread rapidly throughout the region. The more Jesus urged the man to stay quiet, the more the news blazed abroad, igniting excitement and gratitude among those who witnessed the miraculous cure. The fame of Jesus continued to grow, attracting great multitudes of people seeking to hear his teachings and receive healing for their physical ailments and weaknesses.",
            "wordCount": 69,
            "quoteTokenProportion": 27.08,
            "qualityScore": 1.4287762513209512,
            "qualityScoreNormalizedComparedToV2BHTs": 38.85,
            "commentatorTierSimilarities": [
                25.07,
                0.0,
                74.93
            ],
            "generationAttempt": 5
        }
    ]
}