{
    "timestamp": "12-19-2023 16:22:22",
    "verseRef": "Luke 20:45",
    "bestBHT": {
        "bht": "In the hearing of all the people, Jesus drew a full-length portrait of the hypocrisy of the Pharisees and scribes in their presence. This last public appearance of Christ in the temple was a solemn climax where he poured out the vials of his indignation. As witnesses to Jesus' condemnation, the audience of all the people had the opportunity to see the true character of the religious leaders exposed to the world. (39 words)",
        "wordCount": 74,
        "quoteTokenProportion": 38.78,
        "qualityScore": 1.4804969970217896,
        "qualityScoreNormalizedComparedToV2BHTs": 40.57,
        "commentatorTierSimilarities": [
            60.85,
            0.0,
            39.15
        ],
        "generationAttempt": 4
    },
    "choicestQuotes": {
        "Henry Alford": [
            "45.] This particular, in the audience of all the people, is only in Luke."
        ],
        "Archibald T. Robertson": [
            "In the hearing of all the people (\u03b1\u03ba\u03bf\u03c5\u03bf\u03bd\u03c4\u03bf\u03c2 \u03c0\u03b1\u03bd\u03c4\u03bf\u03c2 \u03c4\u03bf\u03c5 \u03bb\u03b1\u03bf\u03c5). Genitive absolute, 'while all the people were listening' (present active participle). That is the time to speak.",
            "Matthew 23:1-39 has a very full and rich description of this last phase of the debate in the temple where Jesus drew a full-length portrait of the hypocrisy of the Pharisees and scribes in their presence.",
            "It was a solemn climax to this last public appearance of Christ in the temple when Jesus poured out the vials of his indignation as he had done before (Matthew 16:2; Luke 11:37-54; Luke 11:12-1)."
        ],
        "John Gill": [
            "Then in the audience of all the people... he said unto his disciples.\" (Quote 1)",
            "Yea, he spake to the multitude, as well as to the disciples.\" (Quote 2)",
            "As well as to the disciples, as appears from Matthew 23:1.\" (Quote 3)"
        ]
    },
    "choicestPrompt": "choicest prompt v0.4",
    "bhtPrompt": "bht prompt v0.8",
    "commentators": [
        "Henry Alford",
        "Jamieson-Fausset-Brown",
        "Albert Barnes",
        "Marvin Vincent",
        "John Calvin",
        "Philip Schaff",
        "Archibald T. Robertson",
        "John Gill",
        "John Wesley"
    ],
    "bhtAttemptsLimit": 5,
    "bhtAttemptsCount": 5,
    "bhtAttempts": [
        {
            "bht": "In the hearing of all the people, Jesus delivered a scathing rebuke to the Pharisees and scribes, exposing their hypocrisy and laying bare their true nature. This climactic moment in the temple was a display of Jesus' righteous indignation, reminiscent of previous instances where he had condemned their actions. The audience of all the people served as witnesses to Jesus' condemnation of the religious leaders, a necessary step in revealing their true character to the world. (37 words)",
            "wordCount": 77,
            "quoteTokenProportion": 27.45,
            "qualityScore": 1.2714088023358656,
            "qualityScoreNormalizedComparedToV2BHTs": 33.62,
            "commentatorTierSimilarities": [
                55.73,
                0.0,
                44.27
            ],
            "generationAttempt": 1
        },
        {
            "bht": "In the hearing of all the people, Jesus poured out the vials of his indignation as he had done before. This last phase of the debate in the temple highlighted the hypocrisy of the Pharisees and scribes, drawing a full-length portrait of their true nature. The solemn climax of Jesus' public appearance served as a witness to his condemnation of the religious leaders, exposing their actions and revealing their true character to the world. (50 words)",
            "wordCount": 76,
            "quoteTokenProportion": 35.29,
            "qualityScore": 1.3640959609175385,
            "qualityScoreNormalizedComparedToV2BHTs": 36.7,
            "commentatorTierSimilarities": [
                59.74,
                0.0,
                40.26
            ],
            "generationAttempt": 2
        },
        {
            "bht": "In the hearing of all the people, Jesus delivered a scathing rebuke to the Pharisees and scribes, exposing their hypocrisy and laying bare their true nature. This climactic moment in the temple was a display of Jesus' righteous indignation, reminiscent of previous instances where he had condemned their actions. The audience of all the people served as witnesses to Jesus' condemnation of the religious leaders, a necessary step in revealing their true character to the world. (50 words)",
            "wordCount": 77,
            "quoteTokenProportion": 27.45,
            "qualityScore": 1.3060021646970583,
            "qualityScoreNormalizedComparedToV2BHTs": 34.77,
            "commentatorTierSimilarities": [
                56.85,
                0.0,
                43.15
            ],
            "generationAttempt": 3
        },
        {
            "bht": "In the hearing of all the people, Jesus drew a full-length portrait of the hypocrisy of the Pharisees and scribes in their presence. This last public appearance of Christ in the temple was a solemn climax where he poured out the vials of his indignation. As witnesses to Jesus' condemnation, the audience of all the people had the opportunity to see the true character of the religious leaders exposed to the world. (39 words)",
            "wordCount": 74,
            "quoteTokenProportion": 38.78,
            "qualityScore": 1.4804969970217896,
            "qualityScoreNormalizedComparedToV2BHTs": 40.57,
            "commentatorTierSimilarities": [
                60.85,
                0.0,
                39.15
            ],
            "generationAttempt": 4
        },
        {
            "bht": "In the hearing of all the people, Jesus poured out the vials of his indignation as he had done before. This last phase of the debate in the temple highlighted the hypocrisy of the Pharisees and scribes, drawing a full-length portrait of their true nature. The solemn climax of Jesus' public appearance served as a witness to his condemnation of the religious leaders, exposing their actions and revealing their true character to the world. (50 words)",
            "wordCount": 76,
            "quoteTokenProportion": 35.29,
            "qualityScore": 1.3640959609175385,
            "qualityScoreNormalizedComparedToV2BHTs": 36.7,
            "commentatorTierSimilarities": [
                59.74,
                0.0,
                40.26
            ],
            "generationAttempt": 5
        }
    ]
}