{
    "timestamp": "12-25-2023 21:16:19",
    "verseRef": "Matthew 25:43",
    "bestBHT": {
        "bht": "The lack of hospitality towards strangers and failure to provide clothing to the naked, as well as the absence of visits to the sick and imprisoned, are indicative of the conduct and character of those in question. Their behavior stands in direct opposition to that of the righteous, resulting in a distinct sentence. This highlights the vital importance of displaying empathy and support for those who find themselves in vulnerable circumstances.",
        "wordCount": 71,
        "quoteTokenProportion": 34.69,
        "qualityScore": 0.9272853285461213,
        "qualityScoreNormalizedComparedToV2BHTs": 22.18,
        "commentatorTierSimilarities": [
            0.0,
            0.0,
            100.0
        ],
        "generationAttempt": 5
    },
    "choicestQuotes": {
        "John Gill": [
            "I was a stranger, and ye took me not in... naked, and ye clothed me not: sick and in prison, and ye visited me not.\" ",
            "Their conduct, behaviour, and character, are just the reverse of the righteous.",
            "It is no wonder that their sentence is different."
        ]
    },
    "choicestPrompt": "choicest prompt v0.4",
    "bhtPrompt": "bht prompt v0.8",
    "commentators": [
        "Henry Alford",
        "Jamieson-Fausset-Brown",
        "Albert Barnes",
        "Marvin Vincent",
        "John Calvin",
        "Philip Schaff",
        "Archibald T. Robertson",
        "John Gill",
        "John Wesley"
    ],
    "bhtAttemptsLimit": 5,
    "bhtAttemptsCount": 5,
    "bhtAttempts": [
        {
            "bht": "In Matthew 25:43, the passage speaks of those who were not compassionate towards strangers, the naked, and the sick and imprisoned. The commentary describes these individuals as having conduct and character that is completely opposite to the righteous. Their lack of kindness and neglect towards others leads to their different sentencing, emphasizing the importance of compassion and care for those in need.",
            "wordCount": 61,
            "quoteTokenProportion": 37.78,
            "qualityScore": 1.0993575185139615,
            "qualityScoreNormalizedComparedToV2BHTs": 27.9,
            "commentatorTierSimilarities": [
                0.0,
                0.0,
                100.0
            ],
            "generationAttempt": 1
        },
        {
            "bht": "In this verse, it is highlighted that those who failed to show compassion towards strangers, the naked, and the sick and imprisoned will face a different outcome due to their contrasting conduct and character when compared to the righteous. By neglecting to extend kindness and care to those in need, they receive a distinct sentence that underscores the significance of demonstrating compassion and support towards others.",
            "wordCount": 66,
            "quoteTokenProportion": 42.86,
            "qualityScore": 1.0892915796292455,
            "qualityScoreNormalizedComparedToV2BHTs": 27.56,
            "commentatorTierSimilarities": [
                0.0,
                0.0,
                100.0
            ],
            "generationAttempt": 2
        },
        {
            "bht": "Those who refused to provide aid to strangers, neglected to clothe the naked, and failed to visit the sick and imprisoned are described as possessing character that is entirely opposite to the righteous. Consequently, their punishment aptly differs. The passage serves as a reminder of the importance of displaying compassion and extending support to those who are in need.",
            "wordCount": 59,
            "quoteTokenProportion": 30.23,
            "qualityScore": 0.853350425822317,
            "qualityScoreNormalizedComparedToV2BHTs": 19.72,
            "commentatorTierSimilarities": [
                0.0,
                0.0,
                100.0
            ],
            "generationAttempt": 3
        },
        {
            "bht": "As the verse suggests, those who had no mercy for strangers, neglected to clothe the naked, and showed no concern for the sick and imprisoned are depicted as having behavior and character that starkly contrasts that of the righteous. As a result, their sentence deviates from the righteous. This serves as a poignant reminder of the significance of demonstrating compassion and care towards those who are in need.",
            "wordCount": 68,
            "quoteTokenProportion": 38.3,
            "qualityScore": 1.0512750965984243,
            "qualityScoreNormalizedComparedToV2BHTs": 26.3,
            "commentatorTierSimilarities": [
                0.0,
                0.0,
                100.0
            ],
            "generationAttempt": 4
        },
        {
            "bht": "The lack of hospitality towards strangers and failure to provide clothing to the naked, as well as the absence of visits to the sick and imprisoned, are indicative of the conduct and character of those in question. Their behavior stands in direct opposition to that of the righteous, resulting in a distinct sentence. This highlights the vital importance of displaying empathy and support for those who find themselves in vulnerable circumstances.",
            "wordCount": 71,
            "quoteTokenProportion": 34.69,
            "qualityScore": 0.9272853285461213,
            "qualityScoreNormalizedComparedToV2BHTs": 22.18,
            "commentatorTierSimilarities": [
                0.0,
                0.0,
                100.0
            ],
            "generationAttempt": 5
        }
    ]
}